src/__init__.py
src/ayonix.py
ayonix-0.3.7.dist-info/LICENSE
ayonix-0.3.7.dist-info/METADATA
ayonix-0.3.7.dist-info/WHEEL
ayonix-0.3.7.dist-info/entry_points.txt
ayonix-0.3.7.dist-info/top_level.txt
ayonix-0.3.7.dist-info/RECORD
