Metadata-Version: 2.1
Name: ayonix
Version: 0.3.7
Summary: A modern CLI program for API testing
Home-page: https://github.com/Silicon27/call
Author: Silicon27
Author-email: yangsilicon@gmail.com
Classifier: Programming Language :: Python :: 3
Classifier: License :: OSI Approved :: MIT License
Classifier: Operating System :: OS Independent
Requires-Python: >=3.6
License-File: LICENSE
Requires-Dist: requests
